brtp/__init__.py
brtp/benchmarking/__init__.py
brtp/benchmarking/_micro_benchmark.py
brtp/benchmarking/_sleep.py
brtp/benchmarking/_timer.py
brtp/caching/__init__.py
brtp/caching/_per_instance_caching.py
brtp/collections/__init__.py
brtp/collections/_zip_random.py
brtp/compat/__init__.py
brtp/compat/_numba/__init__.py
brtp/compat/_numba/_dummy_numba.py
brtp/compat/_numba/_helpers.py
brtp/formatting/__init__.py
brtp/formatting/_time_duration.py
brtp/math/__init__.py
brtp/math/aggregation/__init__.py
brtp/math/aggregation/_means.py
brtp/math/regression/__init__.py
brtp/math/root_finding/__init__.py
brtp/math/root_finding/_bisection.py
brtp/math/sampling/__init__.py
brtp/math/sampling/_deterministic.py
brtp/math/statistics/__init__.py
brtp/math/utils/__init__.py
brtp/math/utils/_clip.py
brtp/math/utils/_precision.py
brtp/math/utils/_sign.py
brtp/misc/__init__.py
brtp/misc/argument_handling/__init__.py
brtp/misc/argument_handling/_checks.py
brtp/plotting/__init__.py
brtp/plotting/canvas/__init__.py
brtp/plotting/canvas/_canvas.py
brtp/plotting/canvas/_canvas_range.py
brtp/plotting/canvas/_linestyle.py
brtp/plotting/utils/__init__.py
brtp/plotting/utils/_transforms.py
brtp-0.0.17.dist-info/METADATA
brtp-0.0.17.dist-info/WHEEL
brtp-0.0.17.dist-info/licenses/LICENSE
brtp-0.0.17.dist-info/RECORD
