Metadata-Version: 2.4
Name: brtp
Version: 0.0.17
Summary: Collection of personal Python utilities.
Project-URL: Source, https://github.com/bertpl/brtp
Project-URL: ChangeLog, https://github.com/bertpl/brtp/blob/main/CHANGELOG.md
Project-URL: Issues, https://github.com/bertpl/brtp/issues
Project-URL: Roadmap, https://github.com/bertpl/brtp/milestones
License-File: LICENSE
Requires-Python: >=3.11
Requires-Dist: matplotlib>=3.9.0
Requires-Dist: numpy>=2.0.0
Provides-Extra: numba
Requires-Dist: numba>=0.57; extra == 'numba'
